LICENSE
README.md
setup.py
dsm_services/__init__.py
dsm_services.egg-info/PKG-INFO
dsm_services.egg-info/SOURCES.txt
dsm_services.egg-info/dependency_links.txt
dsm_services.egg-info/requires.txt
dsm_services.egg-info/top_level.txt
dsm_services/airflow/__init__.py
dsm_services/airflow/utils.py
dsm_services/analyzer/__init__.py
dsm_services/analyzer/analyzer.py
dsm_services/analyzer/utils.py
dsm_services/llm/__init__.py
dsm_services/llm/base.py
dsm_services/llm/langchain.py
dsm_services/monad/__init__.py
dsm_services/monad/resultify.py
dsm_services/nlp/__init__.py
dsm_services/nlp/base.py
dsm_services/nlp/keyword.py
dsm_services/nlp/ner.py
dsm_services/nlp/pos.py
dsm_services/pdf/__init__.py
dsm_services/pdf/base.py
dsm_services/utils/__init__.py
dsm_services/utils/check.py
dsm_services/utils/handle.py