Metadata-Version: 2.2
Name: dsm_services
Version: 0.0.12
Summary: A simple way to use Services
Home-page: https://github.com/storemesh/dsm-services
Author: DigitalStoreMesh Co.,Ltd
Author-email: contact@storemesh.com
License: MIT License
Classifier: Intended Audience :: Developers
Classifier: License :: OSI Approved :: MIT License
Classifier: Operating System :: OS Independent
Classifier: Programming Language :: Python
Classifier: Programming Language :: Python :: 3.7
Classifier: Programming Language :: Python :: 3.8
License-File: LICENSE
Requires-Dist: requests
Requires-Dist: tqdm
Requires-Dist: retry
Dynamic: author
Dynamic: author-email
Dynamic: classifier
Dynamic: description
Dynamic: description-content-type
Dynamic: home-page
Dynamic: license
Dynamic: requires-dist
Dynamic: summary
